depzip/__init__.py
depzip/import.exe
depzip-1.1.dist-info/licenses/LICENSE
depzip-1.1.dist-info/METADATA
depzip-1.1.dist-info/WHEEL
depzip-1.1.dist-info/top_level.txt
depzip-1.1.dist-info/RECORD
