Metadata-Version: 2.4
Name: depzip
Version: 1.1
Summary: A small library for zipping Python application dependencies
Author: Pavel Demin
License-Expression: MIT
Project-URL: Homepage, https://github.com/pavel-demin/depzip
Requires-Python: >=3.12
License-File: LICENSE
Requires-Dist: dllist
Dynamic: license-file
